tdatabase/__init__.py
tdatabase/core.py
tdatabase-1.2.dist-info/LICENSE
tdatabase-1.2.dist-info/METADATA
tdatabase-1.2.dist-info/WHEEL
tdatabase-1.2.dist-info/top_level.txt
tdatabase-1.2.dist-info/RECORD
