Metadata-Version: 2.1
Name: tdatabase
Version: 1.2
Summary: Data Base Made In iran
Author: Tahagaga
License: MIT
Classifier: Programming Language :: Python :: 3
Classifier: License :: OSI Approved :: MIT License
Classifier: Operating System :: OS Independent
Requires-Python: >=3.6
License-File: LICENSE
